{
    "type": "object",
    "title": "Calculate Severities by Items",
    "properties":
                {
                "table": 
                    {
                    "type": "string",
                    "title": "Table Name",
                    "description": "Table to filter by: rnas, categories or subcategories"
                    },
                "items_field": 
                    {
                    "type": "string",
                    "title": "Unique field name",
                    "description": "field in Answers table to filter by: rnaId, categoryId or subCategoryId"
                    },
                "items": 
                    {
                    "type": "array",
                    "title": "Items Partition ID",
                    "items": 
                        {
                        "type": "string"
                        },  
                    "description": "For specific items: [fb91fdc7-46ba-47f8-bc3c-d1e480ad71be, ...] OR [*] for all items"
                    }
                },
    "required": 
            [
            "table",
            "items_field",
            "items"
            ]
}